{"name":"Danu","tagline":"\"Danu\" is a new in developement open source id tek 3 engines RTCW source code game","body":"### Welcome to Danu.\r\nPlease feel free to help develop this wonderful game community. \"Danu\" is a new in developement open source id tek 3 engines RTCW source code game.\r\n\r\n```\r\n$ cd  bretcolin/Danu\r\n$ git fetch origin\r\n$ git checkout gh-pages\r\n\r\n### Authors and Contributors\r\nIn 2013, Bret C. Sheppard (@bretcolin), founded \"Danu\". Hopefully more will contribute and credit will be given.\r\n\r\n### Support or Contact\r\nHaving trouble with Pages? Check out the documentation at http://help.github.com/pages or contact support@github.com and we’ll help you sort it out.\r\n","google":"","note":"Don't delete this file! It's used internally to help with page regeneration."}